LICENSE.txt
MANIFEST.in
README.md
setup.py
dash_core_components/Checklist.py
dash_core_components/ConfirmDialog.py
dash_core_components/ConfirmDialogProvider.py
dash_core_components/DatePickerRange.py
dash_core_components/DatePickerSingle.py
dash_core_components/Dropdown.py
dash_core_components/Graph.py
dash_core_components/Input.py
dash_core_components/Interval.py
dash_core_components/Link.py
dash_core_components/Location.py
dash_core_components/LogoutButton.py
dash_core_components/Markdown.py
dash_core_components/RadioItems.py
dash_core_components/RangeSlider.py
dash_core_components/Slider.py
dash_core_components/Store.py
dash_core_components/SyntaxHighlighter.py
dash_core_components/Tab.py
dash_core_components/Tabs.py
dash_core_components/Textarea.py
dash_core_components/Upload.py
dash_core_components/__init__.py
dash_core_components/_imports_.py
dash_core_components/dash_core_components.dev.js
dash_core_components/dash_core_components.dev.js.map
dash_core_components/dash_core_components.min.js
dash_core_components/dash_core_components.min.js.map
dash_core_components/metadata.json
dash_core_components/plotly-1.44.1.min.js
dash_core_components/version.py
dash_core_components_ppeterson.egg-info/PKG-INFO
dash_core_components_ppeterson.egg-info/SOURCES.txt
dash_core_components_ppeterson.egg-info/dependency_links.txt
dash_core_components_ppeterson.egg-info/requires.txt
dash_core_components_ppeterson.egg-info/top_level.txt
test/test_dash_import.py
test/test_integration.py