Metadata-Version: 1.0
Name: dash-core-components-ppeterson
Version: 0.43.1
Summary: Dash UI core component suite
Home-page: UNKNOWN
Author: Philip Peterson
Author-email: philip.peterson@getcruise.com
License: MIT
Platform: UNKNOWN
